apologiesserver/__init__.py
apologiesserver/cli.py
apologiesserver/config.py
apologiesserver/demo.py
apologiesserver/event.py
apologiesserver/interface.py
apologiesserver/manager.py
apologiesserver/periodic.py
apologiesserver/py.typed
apologiesserver/scheduled.py
apologiesserver/scripts.py
apologiesserver/server.py
apologiesserver/util.py
apologiesserver/validator.py
apologiesserver-0.2.2.dist-info/METADATA
apologiesserver-0.2.2.dist-info/WHEEL
apologiesserver-0.2.2.dist-info/entry_points.txt
apologiesserver-0.2.2.dist-info/licenses/LICENSE
apologiesserver-0.2.2.dist-info/licenses/NOTICE
apologiesserver-0.2.2.dist-info/RECORD
