Metadata-Version: 2.4
Name: apologiesserver
Version: 0.2.2
Summary: Websocket server to interactively play the Apologies game
Project-URL: Homepage, https://pypi.org/project/apologiesserver/
Project-URL: Repository, https://github.com/pronovic/apologies-server
Project-URL: Changelog, https://github.com/pronovic/apologies-server/releases
Project-URL: Documentation, https://apologies-server.readthedocs.io/en/stable/
Project-URL: Issues, https://github.com/pronovic/apologies-server/issues
Author-email: "Kenneth J. Pronovici" <pronovic@ieee.org>
License-Expression: Apache-2.0
License-File: LICENSE
License-File: NOTICE
Classifier: Environment :: Console
Classifier: Intended Audience :: Developers
Classifier: License :: OSI Approved :: Apache Software License
Classifier: Natural Language :: English
Classifier: Operating System :: OS Independent
Classifier: Programming Language :: Python :: 3
Classifier: Programming Language :: Python :: 3.10
Classifier: Topic :: Games/Entertainment :: Board Games
Requires-Python: <4,>=3.11
Requires-Dist: apologies<0.5.0,>=0.4.1
Requires-Dist: ordered-set<5.0.0,>=4.1.0
Requires-Dist: websockets<17.0,>=16.0
Provides-Extra: docs
Requires-Dist: sphinx-autoapi<4.0.0,>=3.0.0; extra == 'docs'
Requires-Dist: sphinx<10.0.0,>=9.0.4; extra == 'docs'
